htrmopo/__init__.py
htrmopo/cli.py
htrmopo/iso15924.txt
htrmopo/iso639-3.txt
htrmopo/licenses.json
htrmopo/publish.py
htrmopo/record.py
htrmopo/repo.py
htrmopo/util.py
htrmopo/v0.metadata.schema.json
htrmopo/v1.metadata.schema.json
htrmopo-0.3.0.dist-info/AUTHORS
htrmopo-0.3.0.dist-info/LICENSE
htrmopo-0.3.0.dist-info/METADATA
htrmopo-0.3.0.dist-info/WHEEL
htrmopo-0.3.0.dist-info/entry_points.txt
htrmopo-0.3.0.dist-info/pbr.json
htrmopo-0.3.0.dist-info/top_level.txt
htrmopo-0.3.0.dist-info/RECORD
