Metadata-Version: 2.2
Name: htrmopo
Version: 0.3.0
Summary: HTRMoPo repository reference implementation
Home-page: http://htrmopo.github.io
Author: Benjamin Kiessling
Author-email: mittagessen@l.unchti.me
License: Apache
Keywords: atr
Classifier: Environment :: Console
Classifier: Intended Audience :: Science/Research
Classifier: License :: OSI Approved :: Apache Software License
Classifier: Operating System :: POSIX
Classifier: Programming Language :: Python :: 3.9
Classifier: Programming Language :: Python :: 3.10
Classifier: Programming Language :: Python :: 3.11
Classifier: Programming Language :: Python :: 3.12
Classifier: Programming Language :: Python :: 3.13
Requires-Python: >=3.9
License-File: LICENSE
License-File: AUTHORS
Requires-Dist: click
Requires-Dist: rich
Requires-Dist: lxml
Requires-Dist: flufl.lock
Requires-Dist: requests
Requires-Dist: pyyaml
Requires-Dist: sickle
Requires-Dist: markdown
Requires-Dist: jsonschema
Requires-Dist: python-dateutil
Requires-Dist: platformdirs
Provides-Extra: test
Requires-Dist: pytest; extra == "test"
Dynamic: author
Dynamic: author-email
Dynamic: classifier
Dynamic: home-page
Dynamic: keywords
Dynamic: license
Dynamic: summary
